ml4xcube/__init__.py
ml4xcube/insights.py
ml4xcube/plotting.py
ml4xcube/postprocessing.py
ml4xcube/preprocessing.py
ml4xcube/splits.py
ml4xcube/utils.py
ml4xcube/datasets/__init__.py
ml4xcube/datasets/chunk_processing.py
ml4xcube/datasets/multiproc_sampler.py
ml4xcube/datasets/pytorch.py
ml4xcube/datasets/tensorflow.py
ml4xcube/datasets/xr_dataset.py
ml4xcube/evaluation/__init__.py
ml4xcube/evaluation/evaluator.py
ml4xcube/evaluation/metrics.py
ml4xcube/gapfilling/__init__.py
ml4xcube/gapfilling/gap_dataset.py
ml4xcube/gapfilling/gap_filling.py
ml4xcube/gapfilling/helper/__init__.py
ml4xcube/gapfilling/helper/predictors.py
ml4xcube/training/__init__.py
ml4xcube/training/pytorch.py
ml4xcube/training/pytorch_distributed.py
ml4xcube/training/sklearn.py
ml4xcube/training/tensorflow.py
ml4xcube/training/train_plots.py
ml4xcube-1.1.0.dist-info/LICENSE
ml4xcube-1.1.0.dist-info/METADATA
ml4xcube-1.1.0.dist-info/WHEEL
ml4xcube-1.1.0.dist-info/top_level.txt
ml4xcube-1.1.0.dist-info/RECORD
