Metadata-Version: 2.1
Name: ml4xcube
Version: 1.1.0
Summary: ML package for data cubes
Author-email: Julia Peters <julia.peters@informatik.uni-leipzig.de>
License: MIT License
Keywords: machine learning,tools,data cube utilities
Classifier: License :: OSI Approved :: MIT License
Requires-Python: >=3.8
License-File: LICENSE
Requires-Dist: dask>=2023.2.0
Requires-Dist: numpy>=1.24
Requires-Dist: pandas>=2.2
Requires-Dist: scikit-learn>1.3.1
Requires-Dist: xarray>2023.8.0
Requires-Dist: zarr>2.11
Requires-Dist: rechunker>=0.5.1
